test-runner
rapidsms_xforms
