Metadata-Version: 1.0
Name: rapidsms-xforms
Version: 0.4.1
Summary: Interactive form builder for both XForms and SMS submissions into RapidSMS
Home-page: http://github.com/nyaruka/rapidsms-xforms
Author: Nicolas Pottier, Eric Newcomer
Author-email: code@nyaruka.com
License: BSD
Download-URL: http://github.com/nyaruka/rapidsms-xforms/downloads
Platform: UNKNOWN
Classifier: Development Status :: 4 - Beta
Classifier: Environment :: Web Environment
Classifier: Intended Audience :: Developers
Classifier: License :: OSI Approved :: BSD License
Classifier: Operating System :: OS Independent
Classifier: Programming Language :: Python
Classifier: Framework :: Django
